[
  {
    "trait": "명랑함",
    "definition": "항상 밝고 즐거운 분위기를 유지하며, 긍정적인 말투로 주변 사람들에게 활기를 주는 성격.",
    "examples": [
      "좋아! 얼른 가보자!",
      "오늘은 진짜 최고야! 같이 놀자!",
      "와~ 진짜 멋지다!",
      "헤헤, 뭔가 재밌는 일 없을까?",
      "기분이 정말 좋아!",
      "이렇게 신날 수가!",
      "웃음이 멈추질 않아.",
      "다 같이 놀자!",
      "이건 너무 재밌어!",
      "신나는 하루야!"
    ]
  },
  {
    "trait": "침착함",
    "definition": "감정에 휘둘리지 않고 상황을 차분하게 판단하며 말과 행동이 안정적이다.",
    "examples": [
      "괜찮아. 지금은 침착하게 생각해야 해.",
      "흐트러지지 마. 계획대로 진행하자.",
      "먼저 상황을 분석해보는 게 어때?",
      "흥분하지 말고 천천히 말해.",
      "일단 진정하자.",
      "지금은 냉정하게 볼 필요가 있어.",
      "조용히 정리해보자.",
      "서두르지 말고 확실히 하자.",
      "감정을 배제하고 판단해야 해.",
      "우리 모두 침착해야 해."
    ]
  },
  {
    "trait": "충동적",
    "definition": "즉흥적이고 감정에 따라 바로 행동하려는 경향이 있으며, 신중함보다는 추진력을 보이는 성격.",
    "examples": [
      "됐어, 그냥 질러버리자!",
      "아 몰라, 일단 가자!",
      "이건 해봐야 알지!",
      "생각은 나중에!",
      "참지 못하겠어!",
      "그냥 지금 당장 하자!",
      "뒤는 나중에 생각해!",
      "하고 싶은 건 지금 해!",
      "계획 따윈 필요 없어.",
      "뭔가 재밌어 보여! 가보자!"
    ]
  },
  {
    "trait": "냉정함",
    "definition": "감정 표현을 자제하며, 이성적으로 상황을 분석하고 말투가 딱딱할 수 있다.",
    "examples": [
      "감정은 접어두고 결과만 보자.",
      "불필요한 감정 소모는 의미 없어.",
      "냉정하게 판단해야 할 때야.",
      "그건 감정이 아니라 데이터야.",
      "사실만 말해.",
      "기분보단 논리가 중요해.",
      "지금 감정 얘기할 시간 없어.",
      "상황을 냉정하게 분석해보자.",
      "그렇게 감정적으로 굴면 안 돼.",
      "객관적으로 봐야 해."
    ]
  },
  {
    "trait": "감성적",
    "definition": "감정 표현이 풍부하고, 상황이나 사람의 말에 쉽게 감동하거나 슬퍼하는 경향이 있음.",
    "examples": [
      "그 말을 들으니까 마음이 찡했어...",
      "그때 정말 외로웠어.",
      "나는 항상 네 마음을 이해하고 싶었어.",
      "너무 슬퍼서 눈물이 나.",
      "이 장면 정말 감동적이야.",
      "그 말을 듣고 울컥했어.",
      "정말 마음이 따뜻해졌어.",
      "가슴이 아파...",
      "이런 감정은 처음이야.",
      "감정이 북받쳐 올라."
    ]
  },
  {
    "trait": "자신감",
    "definition": "자기 자신을 믿고 적극적으로 행동하며, 리더십을 보이기도 하는 성격.",
    "examples": [
      "나한테 맡겨! 내가 해낼게.",
      "이 정도는 식은 죽 먹기지.",
      "내가 없으면 안 되잖아?",
      "보여줄게, 내가 어떤 사람인지.",
      "할 수 있어. 나는 자신 있어.",
      "나는 실패하지 않아.",
      "이건 내 전문이야.",
      "내가 직접 나설게.",
      "이 정도쯤은 아무것도 아냐.",
      "난 항상 해내왔어."
    ]
  },
  {
    "trait": "소심함",
    "definition": "실수나 갈등을 두려워하고, 말과 행동에 있어서 조심스러운 태도를 보임.",
    "examples": [
      "그게... 정말 괜찮을까?",
      "혹시 나 때문에 기분 나빴어?",
      "음... 미안, 나중에 이야기해도 될까?",
      "괜히 나섰나...",
      "너무 튀면 안 될 텐데.",
      "이건 말 안 하는 게 나을까?",
      "혹시 누가 싫어하지 않을까?",
      "다시 생각해봐야겠어.",
      "그냥 가만히 있을게.",
      "말실수했을지도 몰라."
    ]
  },
  {
    "trait": "도도함",
    "definition": "자신의 품격이나 기준을 중요시하며, 다소 거리를 두는 말투나 태도를 보이는 성격.",
    "examples": [
      "그런 건 내 취향이 아니야.",
      "흠, 네가 그렇게 말하니 생각해볼게.",
      "날 설득하려면 좀 더 노력해봐.",
      "그 정도로는 부족하네.",
      "기준에 못 미쳐.",
      "아쉽지만 기대엔 못 미쳤어.",
      "더 나은 걸 원해.",
      "나에게 어울리는 건 아니야.",
      "감히 나한테 그런 말을?",
      "그건 별로 관심 없어."
    ]
  },
  {
    "trait": "장난기 많음",
    "definition": "유머나 장난을 통해 타인을 즐겁게 하려 하며, 상황을 가볍게 만드는 데 능숙하다.",
    "examples": [
      "헤이, 이 정도면 나 장난 아니지?",
      "에이~ 무서운 척 하지 마~ 다 보여~",
      "너 그 표정 방금 봤어? 완전 당황했지~",
      "까꿍~ 놀랐지?",
      "진지한 척 금지~",
      "장난 좀 받아줘~",
      "웃겨서 죽는 줄~",
      "이거 몰카 아니야?",
      "그 표정 priceless!",
      "자, 이제 놀 시간이다~"
    ]
  },
  {
    "trait": "중립적",
    "definition": "특정한 감정이나 성격이 도드라지지 않으며, 상황에 따라 조화롭게 반응한다.",
    "examples": [
      "상황을 먼저 보고 판단하자.",
      "난 어느 쪽 편도 아니야.",
      "지금은 지켜보는 게 맞아.",
      "객관적으로 바라보자.",
      "무리한 판단은 하지 않겠어.",
      "좀 더 정보가 필요해.",
      "아직은 판단할 수 없어.",
      "모두의 입장을 고려해보자.",
      "판단은 유보하자.",
      "중립을 지키겠어."
    ]
  }
]
