{
  "dataset": [
    {
      "id": 1,
      "text": "나 취미가 갖고 싶다",
      "tokens": [
        "나",
        "취미",
        "가",
        "갖",
        "고",
        "싶",
        "다"
      ],
      "metadata": {
        "speaker": "화자_1",
        "source_file": "FACEBOOK_154_10.json",
        "category": "일상대화"
      }
    },
    {
      "id": 2,
      "text": "취미 많은 사람 제일 부러운..",
      "tokens": [
        "취미",
        "많",
        "은",
        "사람",
        "제일",
        "부러운",
        "ETM",
        "."
      ],
      "metadata": {
        "speaker": "화자_2",
        "source_file": "FACEBOOK_154_10.json",
        "category": "일상대화"
      }
    },
    {
      "id": 3,
      "text": "취미 이미 있잖아 키키",
      "tokens": [
        "취미",
        "이미",
        "있",
        "잖아",
        "키",
        "키",
        "ETN"
      ],
      "metadata": {
        "speaker": "화자_3",
        "source_file": "FACEBOOK_154_10.json",
        "category": "일상대화"
      }
    },
    {
      "id": 4,
      "text": "그래서 찾아봤는데 여기 도자기 만드는 곳 있더라구",
      "tokens": [
        "그래서",
        "찾",
        "아",
        "봤",
        "EP",
        "는데",
        "여기",
        "도",
        "자기",
        "만드",
        "는",
        "곳",
        "있",
        "더라구"
      ],
      "metadata": {
        "speaker": "화자_1",
        "source_file": "FACEBOOK_154_10.json",
        "category": "일상대화"
      }
    },
    {
      "id": 5,
      "text": "어떻게 하면 그렇게 하고 싶은 게...",
      "tokens": [
        "어떻게",
        "하",
        "면",
        "그렇게",
        "하",
        "고",
        "싶",
        "은",
        "게",
        "JKS",
        "."
      ],
      "metadata": {
        "speaker": "화자_2",
        "source_file": "FACEBOOK_154_10.json",
        "category": "일상대화"
      }
    },
    {
      "id": 6,
      "text": "낚시가 취미 아닌가 키키",
      "tokens": [
        "낚시",
        "가",
        "취미",
        "아닌가",
        "EC",
        "키",
        "키",
        "ETN"
      ],
      "metadata": {
        "speaker": "화자_3",
        "source_file": "FACEBOOK_154_10.json",
        "category": "일상대화"
      }
    },
    {
      "id": 7,
      "text": "거기 한번 가보려고",
      "tokens": [
        "거기",
        "한",
        "번",
        "가",
        "보",
        "려고"
      ],
      "metadata": {
        "speaker": "화자_1",
        "source_file": "FACEBOOK_154_10.json",
        "category": "일상대화"
      }
    },
    {
      "id": 8,
      "text": "많을 까여?...",
      "tokens": [
        "많",
        "을까",
        "여",
        "EF",
        ".",
        "."
      ],
      "metadata": {
        "speaker": "화자_2",
        "source_file": "FACEBOOK_154_10.json",
        "category": "일상대화"
      }
    },
    {
      "id": 9,
      "text": "낚시도 취미져",
      "tokens": [
        "낚시",
        "도",
        "취미",
        "져"
      ],
      "metadata": {
        "speaker": "화자_2",
        "source_file": "FACEBOOK_154_10.json",
        "category": "일상대화"
      }
    },
    {
      "id": 10,
      "text": "도자기도 재밌겠다 키키",
      "tokens": [
        "도자기",
        "도",
        "재밌",
        "겠",
        "다키키"
      ],
      "metadata": {
        "speaker": "화자_3",
        "source_file": "FACEBOOK_154_10.json",
        "category": "일상대화"
      }
    },
    {
      "id": 11,
      "text": "낚시는 좀 손목이 아픔",
      "tokens": [
        "낚시",
        "는",
        "좀",
        "손목",
        "이",
        "아픔"
      ],
      "metadata": {
        "speaker": "화자_1",
        "source_file": "FACEBOOK_154_10.json",
        "category": "일상대화"
      }
    },
    {
      "id": 12,
      "text": "누나는 취미 많은 편 아닌가 키키",
      "tokens": [
        "누나",
        "는",
        "취미",
        "많",
        "은",
        "편",
        "아닌가",
        "EC",
        "키",
        "키",
        "ETN"
      ],
      "metadata": {
        "speaker": "화자_2",
        "source_file": "FACEBOOK_154_10.json",
        "category": "일상대화"
      }
    },
    {
      "id": 13,
      "text": "나도 그거 배워보고 싶어 키키",
      "tokens": [
        "나",
        "도",
        "그거",
        "배워",
        "EC",
        "보",
        "고",
        "싶",
        "어",
        "키",
        "키",
        "ETN"
      ],
      "metadata": {
        "speaker": "화자_3",
        "source_file": "FACEBOOK_154_10.json",
        "category": "일상대화"
      }
    },
    {
      "id": 14,
      "text": "낚시를 하도 오래 하니까",
      "tokens": [
        "낚시",
        "를",
        "하도",
        "오래",
        "하",
        "니까"
      ],
      "metadata": {
        "speaker": "화자_1",
        "source_file": "FACEBOOK_154_10.json",
        "category": "일상대화"
      }
    },
    {
      "id": 15,
      "text": "도자기 진짜 만들면",
      "tokens": [
        "도자기",
        "진짜",
        "만들",
        "면"
      ],
      "metadata": {
        "speaker": "화자_2",
        "source_file": "FACEBOOK_154_10.json",
        "category": "일상대화"
      }
    },
    {
      "id": 16,
      "text": "아 손목 보호대를 하지?",
      "tokens": [
        "아손",
        "목보",
        "호대",
        "를",
        "하",
        "지"
      ],
      "metadata": {
        "speaker": "화자_3",
        "source_file": "FACEBOOK_154_10.json",
        "category": "일상대화"
      }
    },
    {
      "id": 17,
      "text": "그래서 도자기가 어떨까?",
      "tokens": [
        "그래서",
        "도",
        "자기",
        "가",
        "어떨까",
        "EF"
      ],
      "metadata": {
        "speaker": "화자_1",
        "source_file": "FACEBOOK_154_10.json",
        "category": "일상대화"
      }
    },
    {
      "id": 18,
      "text": "뭔가 마음의 안정이 될 듯...",
      "tokens": [
        "뭔가",
        "VCP",
        "EC",
        "마음",
        "의",
        "안정",
        "이",
        "될",
        "ETM",
        "듯",
        "."
      ],
      "metadata": {
        "speaker": "화자_2",
        "source_file": "FACEBOOK_154_10.json",
        "category": "일상대화"
      }
    },
    {
      "id": 19,
      "text": "그거 하면 좀 덜할 듯?",
      "tokens": [
        "그거",
        "하",
        "면",
        "좀",
        "덜할",
        "ETM",
        "듯"
      ],
      "metadata": {
        "speaker": "화자_3",
        "source_file": "FACEBOOK_154_10.json",
        "category": "일상대화"
      }
    }
  ]
}