{
  "dataset": [
    {
      "id": 1,
      "text": "스벅은 수다 떨기가 민망하다",
      "tokens": [
        "스",
        "벅",
        "은",
        "수다",
        "떨기",
        "가",
        "민망",
        "하",
        "다"
      ],
      "metadata": {
        "speaker": "화자_1",
        "source_file": "FACEBOOK_194_01.json",
        "category": "일상대화"
      }
    },
    {
      "id": 2,
      "text": "거기 카공족 많지",
      "tokens": [
        "거기",
        "카",
        "공족",
        "많",
        "지"
      ],
      "metadata": {
        "speaker": "화자_2",
        "source_file": "FACEBOOK_194_01.json",
        "category": "일상대화"
      }
    },
    {
      "id": 3,
      "text": "난 이제 따뜻한 아메리카노 먹는다",
      "tokens": [
        "난",
        "JX",
        "이제",
        "따뜻",
        "한",
        "ETM",
        "아메리카노",
        "먹",
        "는다"
      ],
      "metadata": {
        "speaker": "화자_3",
        "source_file": "FACEBOOK_194_01.json",
        "category": "일상대화"
      }
    },
    {
      "id": 4,
      "text": "얼죽아는 안됨",
      "tokens": [
        "얼",
        "죽",
        "아",
        "는",
        "안",
        "됨",
        "ETN"
      ],
      "metadata": {
        "speaker": "화자_3",
        "source_file": "FACEBOOK_194_01.json",
        "category": "일상대화"
      }
    },
    {
      "id": 5,
      "text": "거기 왜 이렇게 공부족들...",
      "tokens": [
        "거기",
        "왜",
        "이렇게",
        "공부",
        "족",
        "들",
        "."
      ],
      "metadata": {
        "speaker": "화자_1",
        "source_file": "FACEBOOK_194_01.json",
        "category": "일상대화"
      }
    },
    {
      "id": 6,
      "text": "항상 가면 다들 공부하더라",
      "tokens": [
        "항상",
        "가",
        "면",
        "다",
        "들",
        "공부",
        "하",
        "더라"
      ],
      "metadata": {
        "speaker": "화자_2",
        "source_file": "FACEBOOK_194_01.json",
        "category": "일상대화"
      }
    },
    {
      "id": 7,
      "text": "솔직히 말해봐",
      "tokens": [
        "솔직히",
        "말",
        "해",
        "EC",
        "봐",
        "EC"
      ],
      "metadata": {
        "speaker": "화자_3",
        "source_file": "FACEBOOK_194_01.json",
        "category": "일상대화"
      }
    },
    {
      "id": 8,
      "text": "스벅 왜 감",
      "tokens": [
        "스",
        "벅",
        "왜감"
      ],
      "metadata": {
        "speaker": "화자_3",
        "source_file": "FACEBOOK_194_01.json",
        "category": "일상대화"
      }
    },
    {
      "id": 9,
      "text": "최악임",
      "tokens": [
        "최악",
        "임",
        "ETN"
      ],
      "metadata": {
        "speaker": "화자_1",
        "source_file": "FACEBOOK_194_01.json",
        "category": "일상대화"
      }
    },
    {
      "id": 10,
      "text": "걔네는 왜 거기 와서 죽치고",
      "tokens": [
        "걔",
        "네",
        "는",
        "왜",
        "거기",
        "와서",
        "EC",
        "죽치",
        "고"
      ],
      "metadata": {
        "speaker": "화자_1",
        "source_file": "FACEBOOK_194_01.json",
        "category": "일상대화"
      }
    },
    {
      "id": 11,
      "text": "내 말",
      "tokens": [
        "내",
        "JKG",
        "말"
      ],
      "metadata": {
        "speaker": "화자_2",
        "source_file": "FACEBOOK_194_01.json",
        "category": "일상대화"
      }
    },
    {
      "id": 12,
      "text": "많아서 스트레스 ㅠ",
      "tokens": [
        "많아서스트레스ㅠ"
      ],
      "metadata": {
        "speaker": "화자_2",
        "source_file": "FACEBOOK_194_01.json",
        "category": "일상대화"
      }
    },
    {
      "id": 13,
      "text": "거기 커피 맛도 없고",
      "tokens": [
        "거기",
        "커피",
        "맛",
        "도",
        "없",
        "고"
      ],
      "metadata": {
        "speaker": "화자_3",
        "source_file": "FACEBOOK_194_01.json",
        "category": "일상대화"
      }
    },
    {
      "id": 14,
      "text": "스벅 커피가 난 맛있던데...",
      "tokens": [
        "스",
        "벅",
        "커피",
        "가",
        "난",
        "JX",
        "맛있",
        "던데",
        "."
      ],
      "metadata": {
        "speaker": "화자_1",
        "source_file": "FACEBOOK_194_01.json",
        "category": "일상대화"
      }
    },
    {
      "id": 15,
      "text": "근데 카페 2층짜리는 다 카공족 ㅠㅠ",
      "tokens": [
        "근데",
        "카페",
        "2",
        "층짜리는다카공족ㅠㅠ"
      ],
      "metadata": {
        "speaker": "화자_2",
        "source_file": "FACEBOOK_194_01.json",
        "category": "일상대화"
      }
    },
    {
      "id": 16,
      "text": "책상도 낮아서 책도 안 읽힘",
      "tokens": [
        "책상",
        "도",
        "낮",
        "아서",
        "책",
        "도",
        "안",
        "읽힘",
        "ETN"
      ],
      "metadata": {
        "speaker": "화자_3",
        "source_file": "FACEBOOK_194_01.json",
        "category": "일상대화"
      }
    },
    {
      "id": 17,
      "text": "꼬솜하이 내 스타일임",
      "tokens": [
        "꼬",
        "EC",
        "솜",
        "하",
        "이내",
        "스타일",
        "임",
        "ETN"
      ],
      "metadata": {
        "speaker": "화자_1",
        "source_file": "FACEBOOK_194_01.json",
        "category": "일상대화"
      }
    },
    {
      "id": 18,
      "text": "스벅 자몽허니 그거 맛있음 키키",
      "tokens": [
        "스",
        "벅",
        "자몽",
        "허",
        "EP",
        "니",
        "그거",
        "맛있",
        "음",
        "키",
        "키",
        "ETN"
      ],
      "metadata": {
        "speaker": "화자_2",
        "source_file": "FACEBOOK_194_01.json",
        "category": "일상대화"
      }
    },
    {
      "id": 19,
      "text": "스벅 아메리카노 그 쓴맛이 ?",
      "tokens": [
        "스",
        "벅",
        "아메리카노",
        "그",
        "쓴맛",
        "이"
      ],
      "metadata": {
        "speaker": "화자_3",
        "source_file": "FACEBOOK_194_01.json",
        "category": "일상대화"
      }
    },
    {
      "id": 20,
      "text": "근데 난 거의 드라이브 스루",
      "tokens": [
        "근데",
        "난",
        "JX",
        "거의",
        "드라이브",
        "스루"
      ],
      "metadata": {
        "speaker": "화자_1",
        "source_file": "FACEBOOK_194_01.json",
        "category": "일상대화"
      }
    },
    {
      "id": 21,
      "text": "드라이브 스루가 짱 편하고 좋지",
      "tokens": [
        "드라이브",
        "스루",
        "가",
        "짱",
        "편하",
        "고",
        "좋",
        "지"
      ],
      "metadata": {
        "speaker": "화자_2",
        "source_file": "FACEBOOK_194_01.json",
        "category": "일상대화"
      }
    },
    {
      "id": 22,
      "text": "** 키키 근데 스벅 전문가던데",
      "tokens": [
        "*",
        "*",
        "키키근데스벅전문가던데"
      ],
      "metadata": {
        "speaker": "화자_3",
        "source_file": "FACEBOOK_194_01.json",
        "category": "일상대화"
      }
    }
  ]
}