{
  "dataset": [
    {
      "id": 1,
      "text": "이번에 귤 나와서 먹어봤는데 생각보다 맛없음!",
      "tokens": [
        "이번",
        "에",
        "귤",
        "나와서",
        "EC",
        "먹",
        "어",
        "봤",
        "EP",
        "는데",
        "생각",
        "보다",
        "맛없",
        "음"
      ],
      "metadata": {
        "speaker": "화자_1",
        "source_file": "FACEBOOK_111_01.json",
        "category": "일상대화"
      }
    },
    {
      "id": 2,
      "text": "귤? 귤이 벌써 나오나?",
      "tokens": [
        "귤",
        "?",
        "귤",
        "이",
        "벌써",
        "나오",
        "나"
      ],
      "metadata": {
        "speaker": "화자_2",
        "source_file": "FACEBOOK_111_01.json",
        "category": "일상대화"
      }
    },
    {
      "id": 3,
      "text": "엉 하우스 귤이라고 트럭 아저씨가 팔더라고!",
      "tokens": [
        "엉",
        "하우스",
        "귤",
        "이",
        "라고",
        "트럭",
        "아저씨",
        "가",
        "팔",
        "더라고"
      ],
      "metadata": {
        "speaker": "화자_1",
        "source_file": "FACEBOOK_111_01.json",
        "category": "일상대화"
      }
    },
    {
      "id": 4,
      "text": "키키 하우스에 키운 거는 맛 없지!",
      "tokens": [
        "키키",
        "하우스",
        "에",
        "키운",
        "ETM",
        "거",
        "는",
        "맛없",
        "지"
      ],
      "metadata": {
        "speaker": "화자_2",
        "source_file": "FACEBOOK_111_01.json",
        "category": "일상대화"
      }
    },
    {
      "id": 5,
      "text": "아니야 요즘에는 하우스 귤이 더 맛있다 했단 말이야!",
      "tokens": [
        "아니야",
        "요즘",
        "에",
        "는",
        "하우스",
        "귤",
        "이",
        "더",
        "맛있",
        "다",
        "했",
        "EP",
        "단",
        "말",
        "이",
        "야"
      ],
      "metadata": {
        "speaker": "화자_1",
        "source_file": "FACEBOOK_111_01.json",
        "category": "일상대화"
      }
    },
    {
      "id": 6,
      "text": "트럭에 파는 거는 안 싱싱한 거 같아 ㅠㅠ",
      "tokens": [
        "트럭",
        "에",
        "파",
        "는",
        "거",
        "는",
        "안",
        "싱싱",
        "한",
        "ETM",
        "거",
        "같",
        "아",
        "ㅠㅠ"
      ],
      "metadata": {
        "speaker": "화자_2",
        "source_file": "FACEBOOK_111_01.json",
        "category": "일상대화"
      }
    },
    {
      "id": 7,
      "text": "흠, 그런 거 같아,",
      "tokens": [
        "흠",
        ",",
        "그런",
        "거",
        "같",
        "아",
        ","
      ],
      "metadata": {
        "speaker": "화자_1",
        "source_file": "FACEBOOK_111_01.json",
        "category": "일상대화"
      }
    },
    {
      "id": 8,
      "text": "귤 한 바구니에 3천 원 주긴 했는데!",
      "tokens": [
        "귤",
        "한",
        "ETM",
        "바구니",
        "에",
        "3",
        "천",
        "원",
        "주",
        "긴",
        "JX",
        "했",
        "EP",
        "는데"
      ],
      "metadata": {
        "speaker": "화자_1",
        "source_file": "FACEBOOK_111_01.json",
        "category": "일상대화"
      }
    },
    {
      "id": 9,
      "text": "나 요즘 물가를 몰라서 비싼 건지 몰라 키키",
      "tokens": [
        "나",
        "요즘",
        "물가",
        "를",
        "몰라서",
        "EC",
        "비싼",
        "ETM",
        "건지",
        "VCP",
        "EC",
        "몰라",
        "EC",
        "키",
        "키",
        "ETN"
      ],
      "metadata": {
        "speaker": "화자_2",
        "source_file": "FACEBOOK_111_01.json",
        "category": "일상대화"
      }
    },
    {
      "id": 10,
      "text": "키키 실은 나도,",
      "tokens": [
        "키",
        "키",
        "ETN",
        "실은",
        "나",
        "도",
        ","
      ],
      "metadata": {
        "speaker": "화자_1",
        "source_file": "FACEBOOK_111_01.json",
        "category": "일상대화"
      }
    },
    {
      "id": 11,
      "text": "저번에 엄마가 마트에서 10키로 짜리 2만 원 주고 사왔던 거 같은데!?",
      "tokens": [
        "저번",
        "에",
        "엄마",
        "가",
        "마트",
        "에서",
        "10",
        "키로",
        "ETN",
        "JKB",
        "짜리",
        "2",
        "만",
        "원",
        "주",
        "고",
        "사",
        "EC",
        "왔",
        "EP",
        "던",
        "거",
        "같",
        "은데",
        "!"
      ],
      "metadata": {
        "speaker": "화자_1",
        "source_file": "FACEBOOK_111_01.json",
        "category": "일상대화"
      }
    },
    {
      "id": 12,
      "text": "귤 얘기하니까 귤 먹고 싶다 ㅠㅠ",
      "tokens": [
        "귤",
        "얘기",
        "하",
        "니까",
        "귤",
        "먹",
        "고",
        "싶",
        "다",
        "ㅠㅠ"
      ],
      "metadata": {
        "speaker": "화자_2",
        "source_file": "FACEBOOK_111_01.json",
        "category": "일상대화"
      }
    },
    {
      "id": 13,
      "text": "아 진짜! 귤은 껍질이 얇은 게 맛있어!",
      "tokens": [
        "아",
        "진짜",
        "귤",
        "은",
        "껍질",
        "이",
        "얇",
        "은",
        "게",
        "JKS",
        "맛있",
        "어"
      ],
      "metadata": {
        "speaker": "화자_1",
        "source_file": "FACEBOOK_111_01.json",
        "category": "일상대화"
      }
    },
    {
      "id": 14,
      "text": "오, 얇은 건 어떻게 알아?",
      "tokens": [
        "오",
        ",",
        "얇",
        "은",
        "건",
        "JX",
        "어떻",
        "게",
        "알",
        "아"
      ],
      "metadata": {
        "speaker": "화자_2",
        "source_file": "FACEBOOK_111_01.json",
        "category": "일상대화"
      }
    },
    {
      "id": 15,
      "text": "그 귤 중에 크고 귤이 흐물흐물한 거 몰라! 그거는 맛 없어!",
      "tokens": [
        "그",
        "귤",
        "중",
        "에",
        "크",
        "고",
        "귤",
        "이",
        "흐물흐물",
        "한",
        "ETM",
        "거",
        "몰라",
        "EF",
        "그거",
        "는",
        "맛없",
        "어"
      ],
      "metadata": {
        "speaker": "화자_1",
        "source_file": "FACEBOOK_111_01.json",
        "category": "일상대화"
      }
    },
    {
      "id": 16,
      "text": "오, 이런 꿀팁 고맙다 키키",
      "tokens": [
        "오",
        ",",
        "이런",
        "꿀",
        "팁",
        "고맙",
        "다키키"
      ],
      "metadata": {
        "speaker": "화자_2",
        "source_file": "FACEBOOK_111_01.json",
        "category": "일상대화"
      }
    },
    {
      "id": 17,
      "text": "작고 귀엽고 나같이 생긴 게 맛있지~",
      "tokens": [
        "작",
        "고",
        "귀엽",
        "고",
        "나",
        "같이",
        "생긴",
        "ETM",
        "게",
        "JKS",
        "맛있",
        "지",
        "~"
      ],
      "metadata": {
        "speaker": "화자_1",
        "source_file": "FACEBOOK_111_01.json",
        "category": "일상대화"
      }
    },
    {
      "id": 18,
      "text": "그러면 맛 없을 거 같아!",
      "tokens": [
        "그러면",
        "맛없",
        "을",
        "거",
        "같",
        "아"
      ],
      "metadata": {
        "speaker": "화자_2",
        "source_file": "FACEBOOK_111_01.json",
        "category": "일상대화"
      }
    }
  ]
}